{"name":"Aiden","alltime":{"total_F":2120,"total_M":252629,"total":254749,"fixedness":0.9825,"temporal_fixedness":0.8398,"stability":0.8547,"p_female_smooth":0.0084,"dominant_gender":"M","dominant_pct":99.2,"peak_year":2009,"peak_count":16142,"recent_avg_per_year":7572},"yearly":[{"year":1880,"F":0,"M":0,"total":0,"fixedness":0.0,"p_female_smooth":0.5,"confidence":0.0},{"year":1881,"F":0,"M":0,"total":0,"fixedness":0.0,"p_female_smooth":0.5,"confidence":0.0},{"year":1882,"F":0,"M":0,"total":0,"fixedness":0.0,"p_female_smooth":0.5,"confidence":0.0},{"year":1883,"F":0,"M":0,"total":0,"fixedness":0.0,"p_female_smooth":0.5,"confidence":0.0},{"year":1884,"F":0,"M":0,"total":0,"fixedness":0.0,"p_female_smooth":0.5,"confidence":0.0},{"year":1885,"F":0,"M":0,"total":0,"fixedness":0.0,"p_female_smooth":0.5,"confidence":0.0},{"year":1886,"F":0,"M":0,"total":0,"fixedness":0.0,"p_female_smooth":0.5,"confidence":0.0},{"year":1887,"F":0,"M":0,"total":0,"fixedness":0.0,"p_female_smooth":0.5,"confidence":0.0},{"year":1888,"F":0,"M":0,"total":0,"fixedness":0.0,"p_female_smooth":0.5,"confidence":0.0},{"year":1889,"F":0,"M":0,"total":0,"fixedness":0.0,"p_female_smooth":0.5,"confidence":0.0},{"year":1890,"F":0,"M":0,"total":0,"fixedness":0.0,"p_female_smooth":0.5,"confidence":0.0},{"year":1891,"F":0,"M":0,"total":0,"fixedness":0.0,"p_female_smooth":0.5,"confidence":0.0},{"year":1892,"F":0,"M":0,"total":0,"fixedness":0.0,"p_female_smooth":0.5,"confidence":0.0},{"year":1893,"F":0,"M":0,"total":0,"fixedness":0.0,"p_female_smooth":0.5,"confidence":0.0},{"year":1894,"F":0,"M":0,"total":0,"fixedness":0.0,"p_female_smooth":0.5,"confidence":0.0},{"year":1895,"F":0,"M":0,"total":0,"fixedness":0.0,"p_female_smooth":0.5,"confidence":0.0},{"year":1896,"F":0,"M":0,"total":0,"fixedness":0.0,"p_female_smooth":0.5,"confidence":0.0},{"year":1897,"F":0,"M":0,"total":0,"fixedness":0.0,"p_female_smooth":0.5,"confidence":0.0},{"year":1898,"F":0,"M":0,"total":0,"fixedness":0.0,"p_female_smooth":0.5,"confidence":0.0},{"year":1899,"F":0,"M":0,"total":0,"fixedness":0.0,"p_female_smooth":0.5,"confidence":0.0},{"year":1900,"F":0,"M":0,"total":0,"fixedness":0.0,"p_female_smooth":0.5,"confidence":0.0},{"year":1901,"F":0,"M":0,"total":0,"fixedness":0.0,"p_female_smooth":0.5,"confidence":0.0},{"year":1902,"F":0,"M":0,"total":0,"fixedness":0.0,"p_female_smooth":0.5,"confidence":0.0},{"year":1903,"F":0,"M":0,"total":0,"fixedness":0.0,"p_female_smooth":0.5,"confidence":0.0},{"year":1904,"F":0,"M":0,"total":0,"fixedness":0.0,"p_female_smooth":0.5,"confidence":0.0},{"year":1905,"F":0,"M":0,"total":0,"fixedness":0.0,"p_female_smooth":0.5,"confidence":0.0},{"year":1906,"F":0,"M":0,"total":0,"fixedness":0.0,"p_female_smooth":0.5,"confidence":0.0},{"year":1907,"F":0,"M":0,"total":0,"fixedness":0.0,"p_female_smooth":0.5,"confidence":0.0},{"year":1908,"F":0,"M":0,"total":0,"fixedness":0.0,"p_female_smooth":0.5,"confidence":0.0},{"year":1909,"F":0,"M":0,"total":0,"fixedness":0.0,"p_female_smooth":0.5,"confidence":0.0},{"year":1910,"F":0,"M":0,"total":0,"fixedness":0.0,"p_female_smooth":0.5,"confidence":0.0},{"year":1911,"F":0,"M":0,"total":0,"fixedness":0.0,"p_female_smooth":0.5,"confidence":0.0},{"year":1912,"F":0,"M":0,"total":0,"fixedness":0.0,"p_female_smooth":0.5,"confidence":0.0},{"year":1913,"F":0,"M":0,"total":0,"fixedness":0.0,"p_female_smooth":0.5,"confidence":0.0},{"year":1914,"F":0,"M":0,"total":0,"fixedness":0.0,"p_female_smooth":0.5,"confidence":0.0},{"year":1915,"F":0,"M":0,"total":0,"fixedness":0.0,"p_female_smooth":0.5,"confidence":0.0},{"year":1916,"F":0,"M":0,"total":0,"fixedness":0.0,"p_female_smooth":0.5,"confidence":0.0},{"year":1917,"F":0,"M":0,"total":0,"fixedness":0.0,"p_female_smooth":0.5,"confidence":0.0},{"year":1918,"F":0,"M":0,"total":0,"fixedness":0.0,"p_female_smooth":0.5,"confidence":0.0},{"year":1919,"F":0,"M":0,"total":0,"fixedness":0.0,"p_female_smooth":0.5,"confidence":0.0},{"year":1920,"F":0,"M":0,"total":0,"fixedness":0.0,"p_female_smooth":0.5,"confidence":0.0},{"year":1921,"F":0,"M":0,"total":0,"fixedness":0.0,"p_female_smooth":0.5,"confidence":0.0},{"year":1922,"F":0,"M":0,"total":0,"fixedness":0.0,"p_female_smooth":0.5,"confidence":0.0},{"year":1923,"F":0,"M":0,"total":0,"fixedness":0.0,"p_female_smooth":0.5,"confidence":0.0},{"year":1924,"F":0,"M":0,"total":0,"fixedness":0.0,"p_female_smooth":0.5,"confidence":0.0},{"year":1925,"F":0,"M":0,"total":0,"fixedness":0.0,"p_female_smooth":0.5,"confidence":0.0},{"year":1926,"F":0,"M":0,"total":0,"fixedness":0.0,"p_female_smooth":0.5,"confidence":0.0},{"year":1927,"F":0,"M":0,"total":0,"fixedness":0.0,"p_female_smooth":0.5,"confidence":0.0},{"year":1928,"F":0,"M":0,"total":0,"fixedness":0.0,"p_female_smooth":0.5,"confidence":0.0},{"year":1929,"F":0,"M":0,"total":0,"fixedness":0.0,"p_female_smooth":0.5,"confidence":0.0},{"year":1930,"F":0,"M":0,"total":0,"fixedness":0.0,"p_female_smooth":0.5,"confidence":0.0},{"year":1931,"F":0,"M":0,"total":0,"fixedness":0.0,"p_female_smooth":0.5,"confidence":0.0},{"year":1932,"F":0,"M":0,"total":0,"fixedness":0.0,"p_female_smooth":0.5,"confidence":0.0},{"year":1933,"F":0,"M":0,"total":0,"fixedness":0.0,"p_female_smooth":0.5,"confidence":0.0},{"year":1934,"F":0,"M":0,"total":0,"fixedness":0.0,"p_female_smooth":0.5,"confidence":0.0},{"year":1935,"F":0,"M":0,"total":0,"fixedness":0.0,"p_female_smooth":0.5,"confidence":0.0},{"year":1936,"F":0,"M":0,"total":0,"fixedness":0.0,"p_female_smooth":0.5,"confidence":0.0},{"year":1937,"F":0,"M":0,"total":0,"fixedness":0.0,"p_female_smooth":0.5,"confidence":0.0},{"year":1938,"F":0,"M":0,"total":0,"fixedness":0.0,"p_female_smooth":0.5,"confidence":0.0},{"year":1939,"F":0,"M":0,"total":0,"fixedness":0.0,"p_female_smooth":0.5,"confidence":0.0},{"year":1940,"F":0,"M":0,"total":0,"fixedness":0.0,"p_female_smooth":0.5,"confidence":0.0},{"year":1941,"F":0,"M":0,"total":0,"fixedness":0.0,"p_female_smooth":0.5,"confidence":0.0},{"year":1942,"F":0,"M":0,"total":0,"fixedness":0.0,"p_female_smooth":0.5,"confidence":0.0},{"year":1943,"F":0,"M":0,"total":0,"fixedness":0.0,"p_female_smooth":0.5,"confidence":0.0},{"year":1944,"F":0,"M":0,"total":0,"fixedness":0.0,"p_female_smooth":0.5,"confidence":0.0},{"year":1945,"F":0,"M":0,"total":0,"fixedness":0.0,"p_female_smooth":0.5,"confidence":0.0},{"year":1946,"F":0,"M":0,"total":0,"fixedness":0.0,"p_female_smooth":0.5,"confidence":0.0},{"year":1947,"F":0,"M":0,"total":0,"fixedness":0.0,"p_female_smooth":0.5,"confidence":0.0},{"year":1948,"F":0,"M":0,"total":0,"fixedness":0.0,"p_female_smooth":0.5,"confidence":0.0},{"year":1949,"F":0,"M":0,"total":0,"fixedness":0.0,"p_female_smooth":0.5,"confidence":0.0},{"year":1950,"F":0,"M":0,"total":0,"fixedness":0.0,"p_female_smooth":0.5,"confidence":0.0},{"year":1951,"F":0,"M":0,"total":0,"fixedness":0.0,"p_female_smooth":0.5,"confidence":0.0},{"year":1952,"F":0,"M":0,"total":0,"fixedness":0.0,"p_female_smooth":0.5,"confidence":0.0},{"year":1953,"F":0,"M":0,"total":0,"fixedness":0.0,"p_female_smooth":0.5,"confidence":0.0},{"year":1954,"F":0,"M":0,"total":0,"fixedness":0.0,"p_female_smooth":0.5,"confidence":0.0},{"year":1955,"F":0,"M":0,"total":0,"fixedness":0.0,"p_female_smooth":0.5,"confidence":0.0},{"year":1956,"F":0,"M":0,"total":0,"fixedness":0.0,"p_female_smooth":0.5,"confidence":0.0},{"year":1957,"F":0,"M":0,"total":0,"fixedness":0.0,"p_female_smooth":0.5,"confidence":0.0},{"year":1958,"F":0,"M":0,"total":0,"fixedness":0.0,"p_female_smooth":0.5,"confidence":0.0},{"year":1959,"F":0,"M":0,"total":0,"fixedness":0.0,"p_female_smooth":0.5,"confidence":0.0},{"year":1960,"F":0,"M":0,"total":0,"fixedness":0.0,"p_female_smooth":0.5,"confidence":0.0},{"year":1961,"F":0,"M":0,"total":0,"fixedness":0.0,"p_female_smooth":0.5,"confidence":0.0},{"year":1962,"F":0,"M":0,"total":0,"fixedness":0.0,"p_female_smooth":0.5,"confidence":0.0},{"year":1963,"F":0,"M":0,"total":0,"fixedness":0.0,"p_female_smooth":0.5,"confidence":0.0},{"year":1964,"F":0,"M":0,"total":0,"fixedness":0.0,"p_female_smooth":0.5,"confidence":0.0},{"year":1965,"F":0,"M":0,"total":0,"fixedness":0.0,"p_female_smooth":0.5,"confidence":0.0},{"year":1966,"F":0,"M":0,"total":0,"fixedness":0.0,"p_female_smooth":0.5,"confidence":0.0},{"year":1967,"F":0,"M":0,"total":0,"fixedness":0.0,"p_female_smooth":0.5,"confidence":0.0},{"year":1968,"F":0,"M":0,"total":0,"fixedness":0.0,"p_female_smooth":0.5,"confidence":0.0},{"year":1969,"F":0,"M":0,"total":0,"fixedness":0.0,"p_female_smooth":0.5,"confidence":0.0},{"year":1970,"F":0,"M":6,"total":6,"fixedness":0.0067,"p_female_smooth":0.3846,"confidence":0.0291},{"year":1971,"F":0,"M":0,"total":0,"fixedness":0.0,"p_female_smooth":0.5,"confidence":0.0},{"year":1972,"F":0,"M":0,"total":0,"fixedness":0.0,"p_female_smooth":0.5,"confidence":0.0},{"year":1973,"F":0,"M":0,"total":0,"fixedness":0.0,"p_female_smooth":0.5,"confidence":0.0},{"year":1974,"F":0,"M":0,"total":0,"fixedness":0.0,"p_female_smooth":0.5,"confidence":0.0},{"year":1975,"F":0,"M":7,"total":7,"fixedness":0.0088,"p_female_smooth":0.3704,"confidence":0.0338},{"year":1976,"F":0,"M":0,"total":0,"fixedness":0.0,"p_female_smooth":0.5,"confidence":0.0},{"year":1977,"F":0,"M":5,"total":5,"fixedness":0.0049,"p_female_smooth":0.4,"confidence":0.0244},{"year":1978,"F":0,"M":0,"total":0,"fixedness":0.0,"p_female_smooth":0.5,"confidence":0.0},{"year":1979,"F":0,"M":7,"total":7,"fixedness":0.0088,"p_female_smooth":0.3704,"confidence":0.0338},{"year":1980,"F":0,"M":0,"total":0,"fixedness":0.0,"p_female_smooth":0.5,"confidence":0.0},{"year":1981,"F":0,"M":6,"total":6,"fixedness":0.0067,"p_female_smooth":0.3846,"confidence":0.0291},{"year":1982,"F":0,"M":0,"total":0,"fixedness":0.0,"p_female_smooth":0.5,"confidence":0.0},{"year":1983,"F":0,"M":5,"total":5,"fixedness":0.0049,"p_female_smooth":0.4,"confidence":0.0244},{"year":1984,"F":0,"M":6,"total":6,"fixedness":0.0067,"p_female_smooth":0.3846,"confidence":0.0291},{"year":1985,"F":0,"M":19,"total":19,"fixedness":0.0423,"p_female_smooth":0.2564,"confidence":0.0868},{"year":1986,"F":0,"M":5,"total":5,"fixedness":0.0049,"p_female_smooth":0.4,"confidence":0.0244},{"year":1987,"F":0,"M":7,"total":7,"fixedness":0.0088,"p_female_smooth":0.3704,"confidence":0.0338},{"year":1988,"F":6,"M":14,"total":20,"fixedness":0.0182,"p_female_smooth":0.4,"confidence":0.0909},{"year":1989,"F":5,"M":14,"total":19,"fixedness":0.02,"p_female_smooth":0.3846,"confidence":0.0868},{"year":1990,"F":0,"M":16,"total":16,"fixedness":0.0329,"p_female_smooth":0.2778,"confidence":0.0741},{"year":1991,"F":0,"M":27,"total":27,"fixedness":0.0683,"p_female_smooth":0.2128,"confidence":0.1189},{"year":1992,"F":0,"M":39,"total":39,"fixedness":0.1079,"p_female_smooth":0.1695,"confidence":0.1632},{"year":1993,"F":7,"M":50,"total":57,"fixedness":0.1239,"p_female_smooth":0.2208,"confidence":0.2218},{"year":1994,"F":16,"M":86,"total":102,"fixedness":0.1938,"p_female_smooth":0.2131,"confidence":0.3377},{"year":1995,"F":22,"M":140,"total":162,"fixedness":0.2901,"p_female_smooth":0.1758,"confidence":0.4475},{"year":1996,"F":18,"M":174,"total":192,"fixedness":0.3604,"p_female_smooth":0.1321,"confidence":0.4898},{"year":1997,"F":32,"M":264,"total":296,"fixedness":0.4381,"p_female_smooth":0.1329,"confidence":0.5968},{"year":1998,"F":30,"M":367,"total":397,"fixedness":0.5374,"p_female_smooth":0.0959,"confidence":0.665},{"year":1999,"F":34,"M":479,"total":513,"fixedness":0.6007,"p_female_smooth":0.0826,"confidence":0.7195},{"year":2000,"F":56,"M":881,"total":937,"fixedness":0.7104,"p_female_smooth":0.069,"confidence":0.8241},{"year":2001,"F":67,"M":1587,"total":1654,"fixedness":0.8101,"p_female_smooth":0.046,"confidence":0.8921},{"year":2002,"F":78,"M":2832,"total":2910,"fixedness":0.8795,"p_female_smooth":0.03,"confidence":0.9357},{"year":2003,"F":106,"M":5684,"total":5790,"fixedness":0.928,"p_female_smooth":0.02,"confidence":0.9666},{"year":2004,"F":123,"M":7161,"total":7284,"fixedness":0.9378,"p_female_smooth":0.0182,"confidence":0.9733},{"year":2005,"F":129,"M":9083,"total":9212,"fixedness":0.9493,"p_female_smooth":0.0151,"confidence":0.9788},{"year":2006,"F":140,"M":11591,"total":11731,"fixedness":0.9581,"p_female_smooth":0.0128,"confidence":0.9832},{"year":2007,"F":176,"M":13113,"total":13289,"fixedness":0.9576,"p_female_smooth":0.014,"confidence":0.9852},{"year":2008,"F":141,"M":15590,"total":15731,"fixedness":0.9685,"p_female_smooth":0.0096,"confidence":0.9874},{"year":2009,"F":113,"M":16029,"total":16142,"fixedness":0.9727,"p_female_smooth":0.0076,"confidence":0.9878},{"year":2010,"F":108,"M":15546,"total":15654,"fixedness":0.9725,"p_female_smooth":0.0075,"confidence":0.9874},{"year":2011,"F":92,"M":15518,"total":15610,"fixedness":0.9745,"p_female_smooth":0.0065,"confidence":0.9873},{"year":2012,"F":88,"M":14924,"total":15012,"fixedness":0.974,"p_female_smooth":0.0065,"confidence":0.9869},{"year":2013,"F":74,"M":13646,"total":13720,"fixedness":0.9736,"p_female_smooth":0.0061,"confidence":0.9856},{"year":2014,"F":58,"M":13436,"total":13494,"fixedness":0.9755,"p_female_smooth":0.005,"confidence":0.9854},{"year":2015,"F":60,"M":13504,"total":13564,"fixedness":0.9753,"p_female_smooth":0.0052,"confidence":0.9855},{"year":2016,"F":42,"M":12265,"total":12307,"fixedness":0.9757,"p_female_smooth":0.0042,"confidence":0.984},{"year":2017,"F":44,"M":11352,"total":11396,"fixedness":0.9735,"p_female_smooth":0.0047,"confidence":0.9828},{"year":2018,"F":37,"M":10058,"total":10095,"fixedness":0.9715,"p_female_smooth":0.0046,"confidence":0.9806},{"year":2019,"F":44,"M":9399,"total":9443,"fixedness":0.9681,"p_female_smooth":0.0057,"confidence":0.9793},{"year":2020,"F":49,"M":8613,"total":8662,"fixedness":0.9641,"p_female_smooth":0.0068,"confidence":0.9774},{"year":2021,"F":30,"M":8304,"total":8334,"fixedness":0.9672,"p_female_smooth":0.0048,"confidence":0.9766},{"year":2022,"F":45,"M":7835,"total":7880,"fixedness":0.9617,"p_female_smooth":0.007,"confidence":0.9752},{"year":2023,"F":25,"M":6692,"total":6717,"fixedness":0.961,"p_female_smooth":0.0052,"confidence":0.9711},{"year":2024,"F":25,"M":6243,"total":6268,"fixedness":0.9583,"p_female_smooth":0.0056,"confidence":0.9691}]}