{"name":"Constance","alltime":{"total_F":139832,"total_M":419,"total":140251,"fixedness":0.9925,"temporal_fixedness":0.9836,"stability":0.991,"p_female_smooth":0.9969,"dominant_gender":"F","dominant_pct":99.7,"peak_year":1950,"peak_count":4451,"recent_avg_per_year":123},"yearly":[{"year":1880,"F":15,"M":0,"total":15,"fixedness":0.0299,"p_female_smooth":0.7143,"confidence":0.0698},{"year":1881,"F":14,"M":0,"total":14,"fixedness":0.0269,"p_female_smooth":0.7059,"confidence":0.0654},{"year":1882,"F":22,"M":0,"total":22,"fixedness":0.0519,"p_female_smooth":0.7619,"confidence":0.0991},{"year":1883,"F":17,"M":0,"total":17,"fixedness":0.036,"p_female_smooth":0.7297,"confidence":0.0783},{"year":1884,"F":29,"M":0,"total":29,"fixedness":0.0749,"p_female_smooth":0.7959,"confidence":0.1266},{"year":1885,"F":31,"M":0,"total":31,"fixedness":0.0816,"p_female_smooth":0.8039,"confidence":0.1342},{"year":1886,"F":36,"M":0,"total":36,"fixedness":0.0981,"p_female_smooth":0.8214,"confidence":0.1525},{"year":1887,"F":37,"M":0,"total":37,"fixedness":0.1013,"p_female_smooth":0.8246,"confidence":0.1561},{"year":1888,"F":43,"M":0,"total":43,"fixedness":0.1208,"p_female_smooth":0.8413,"confidence":0.177},{"year":1889,"F":46,"M":0,"total":46,"fixedness":0.1303,"p_female_smooth":0.8485,"confidence":0.187},{"year":1890,"F":45,"M":0,"total":45,"fixedness":0.1272,"p_female_smooth":0.8462,"confidence":0.1837},{"year":1891,"F":44,"M":0,"total":44,"fixedness":0.124,"p_female_smooth":0.8438,"confidence":0.1803},{"year":1892,"F":60,"M":0,"total":60,"fixedness":0.1731,"p_female_smooth":0.875,"confidence":0.2308},{"year":1893,"F":60,"M":0,"total":60,"fixedness":0.1731,"p_female_smooth":0.875,"confidence":0.2308},{"year":1894,"F":62,"M":0,"total":62,"fixedness":0.1789,"p_female_smooth":0.878,"confidence":0.2366},{"year":1895,"F":90,"M":0,"total":90,"fixedness":0.2539,"p_female_smooth":0.9091,"confidence":0.3103},{"year":1896,"F":75,"M":0,"total":75,"fixedness":0.2153,"p_female_smooth":0.8947,"confidence":0.2727},{"year":1897,"F":82,"M":0,"total":82,"fixedness":0.2338,"p_female_smooth":0.902,"confidence":0.2908},{"year":1898,"F":82,"M":0,"total":82,"fixedness":0.2338,"p_female_smooth":0.902,"confidence":0.2908},{"year":1899,"F":106,"M":0,"total":106,"fixedness":0.2914,"p_female_smooth":0.9206,"confidence":0.3464},{"year":1900,"F":112,"M":0,"total":112,"fixedness":0.3046,"p_female_smooth":0.9242,"confidence":0.359},{"year":1901,"F":94,"M":0,"total":94,"fixedness":0.2636,"p_female_smooth":0.9123,"confidence":0.3197},{"year":1902,"F":117,"M":0,"total":117,"fixedness":0.3152,"p_female_smooth":0.927,"confidence":0.3691},{"year":1903,"F":144,"M":0,"total":144,"fixedness":0.3676,"p_female_smooth":0.939,"confidence":0.4186},{"year":1904,"F":127,"M":0,"total":127,"fixedness":0.3355,"p_female_smooth":0.932,"confidence":0.3884},{"year":1905,"F":163,"M":0,"total":163,"fixedness":0.4,"p_female_smooth":0.9454,"confidence":0.449},{"year":1906,"F":167,"M":0,"total":167,"fixedness":0.4064,"p_female_smooth":0.9465,"confidence":0.455},{"year":1907,"F":194,"M":0,"total":194,"fixedness":0.4464,"p_female_smooth":0.9533,"confidence":0.4924},{"year":1908,"F":214,"M":0,"total":214,"fixedness":0.4727,"p_female_smooth":0.9573,"confidence":0.5169},{"year":1909,"F":206,"M":0,"total":206,"fixedness":0.4625,"p_female_smooth":0.9558,"confidence":0.5074},{"year":1910,"F":261,"M":0,"total":261,"fixedness":0.5259,"p_female_smooth":0.9644,"confidence":0.5662},{"year":1911,"F":298,"M":0,"total":298,"fixedness":0.5608,"p_female_smooth":0.9686,"confidence":0.5984},{"year":1912,"F":375,"M":0,"total":375,"fixedness":0.6192,"p_female_smooth":0.9747,"confidence":0.6522},{"year":1913,"F":458,"M":0,"total":458,"fixedness":0.6669,"p_female_smooth":0.9791,"confidence":0.696},{"year":1914,"F":600,"M":0,"total":600,"fixedness":0.7258,"p_female_smooth":0.9839,"confidence":0.75},{"year":1915,"F":728,"M":5,"total":733,"fixedness":0.7543,"p_female_smooth":0.9801,"confidence":0.7856},{"year":1916,"F":811,"M":10,"total":821,"fixedness":0.7659,"p_female_smooth":0.9762,"confidence":0.8041},{"year":1917,"F":845,"M":0,"total":845,"fixedness":0.7899,"p_female_smooth":0.9884,"confidence":0.8086},{"year":1918,"F":971,"M":6,"total":977,"fixedness":0.8034,"p_female_smooth":0.984,"confidence":0.8301},{"year":1919,"F":1078,"M":7,"total":1085,"fixedness":0.8184,"p_female_smooth":0.9846,"confidence":0.8444},{"year":1920,"F":1377,"M":6,"total":1383,"fixedness":0.8537,"p_female_smooth":0.9886,"confidence":0.8737},{"year":1921,"F":1686,"M":0,"total":1686,"fixedness":0.8835,"p_female_smooth":0.9941,"confidence":0.894},{"year":1922,"F":1676,"M":8,"total":1684,"fixedness":0.875,"p_female_smooth":0.9894,"confidence":0.8938},{"year":1923,"F":1687,"M":5,"total":1692,"fixedness":0.8786,"p_female_smooth":0.9912,"confidence":0.8943},{"year":1924,"F":1655,"M":7,"total":1662,"fixedness":0.8745,"p_female_smooth":0.9899,"confidence":0.8926},{"year":1925,"F":1654,"M":0,"total":1654,"fixedness":0.8815,"p_female_smooth":0.994,"confidence":0.8921},{"year":1926,"F":1669,"M":11,"total":1680,"fixedness":0.8715,"p_female_smooth":0.9876,"confidence":0.8936},{"year":1927,"F":1521,"M":9,"total":1530,"fixedness":0.8627,"p_female_smooth":0.9877,"confidence":0.8844},{"year":1928,"F":1319,"M":6,"total":1325,"fixedness":0.8482,"p_female_smooth":0.9881,"confidence":0.8689},{"year":1929,"F":1326,"M":13,"total":1339,"fixedness":0.8406,"p_female_smooth":0.9831,"confidence":0.87},{"year":1930,"F":1463,"M":7,"total":1470,"fixedness":0.8602,"p_female_smooth":0.9886,"confidence":0.8802},{"year":1931,"F":2073,"M":7,"total":2080,"fixedness":0.8975,"p_female_smooth":0.9919,"confidence":0.9123},{"year":1932,"F":2492,"M":16,"total":2508,"fixedness":0.9071,"p_female_smooth":0.9897,"confidence":0.9261},{"year":1933,"F":2193,"M":11,"total":2204,"fixedness":0.8995,"p_female_smooth":0.9906,"confidence":0.9168},{"year":1934,"F":1975,"M":10,"total":1985,"fixedness":0.8903,"p_female_smooth":0.99,"confidence":0.9085},{"year":1935,"F":1804,"M":15,"total":1819,"fixedness":0.8764,"p_female_smooth":0.9864,"confidence":0.9009},{"year":1936,"F":1697,"M":6,"total":1703,"fixedness":0.8783,"p_female_smooth":0.9907,"confidence":0.8949},{"year":1937,"F":2029,"M":8,"total":2037,"fixedness":0.8947,"p_female_smooth":0.9912,"confidence":0.9106},{"year":1938,"F":2161,"M":6,"total":2167,"fixedness":0.9021,"p_female_smooth":0.9927,"confidence":0.9155},{"year":1939,"F":2009,"M":14,"total":2023,"fixedness":0.8887,"p_female_smooth":0.9883,"confidence":0.91},{"year":1940,"F":2039,"M":9,"total":2048,"fixedness":0.8943,"p_female_smooth":0.9908,"confidence":0.911},{"year":1941,"F":2275,"M":13,"total":2288,"fixedness":0.9013,"p_female_smooth":0.99,"confidence":0.9196},{"year":1942,"F":2357,"M":15,"total":2372,"fixedness":0.903,"p_female_smooth":0.9895,"confidence":0.9222},{"year":1943,"F":2554,"M":8,"total":2562,"fixedness":0.9147,"p_female_smooth":0.993,"confidence":0.9276},{"year":1944,"F":2634,"M":10,"total":2644,"fixedness":0.9157,"p_female_smooth":0.9925,"confidence":0.9297},{"year":1945,"F":2601,"M":0,"total":2601,"fixedness":0.9215,"p_female_smooth":0.9962,"confidence":0.9286},{"year":1946,"F":3419,"M":7,"total":3426,"fixedness":0.9355,"p_female_smooth":0.9951,"confidence":0.9448},{"year":1947,"F":3894,"M":14,"total":3908,"fixedness":0.9397,"p_female_smooth":0.9939,"confidence":0.9513},{"year":1948,"F":3812,"M":10,"total":3822,"fixedness":0.9404,"p_female_smooth":0.9948,"confidence":0.9503},{"year":1949,"F":4327,"M":9,"total":4336,"fixedness":0.9476,"p_female_smooth":0.9956,"confidence":0.9559},{"year":1950,"F":4441,"M":10,"total":4451,"fixedness":0.9484,"p_female_smooth":0.9955,"confidence":0.957},{"year":1951,"F":4367,"M":8,"total":4375,"fixedness":0.9485,"p_female_smooth":0.9959,"confidence":0.9563},{"year":1952,"F":4116,"M":14,"total":4130,"fixedness":0.9428,"p_female_smooth":0.9942,"confidence":0.9538},{"year":1953,"F":4030,"M":8,"total":4038,"fixedness":0.9444,"p_female_smooth":0.9956,"confidence":0.9528},{"year":1954,"F":3836,"M":6,"total":3842,"fixedness":0.9426,"p_female_smooth":0.9959,"confidence":0.9505},{"year":1955,"F":3662,"M":7,"total":3669,"fixedness":0.9396,"p_female_smooth":0.9954,"confidence":0.9483},{"year":1956,"F":2816,"M":5,"total":2821,"fixedness":0.9239,"p_female_smooth":0.9947,"confidence":0.9338},{"year":1957,"F":2418,"M":5,"total":2423,"fixedness":0.9124,"p_female_smooth":0.9939,"confidence":0.9238},{"year":1958,"F":2000,"M":0,"total":2000,"fixedness":0.9001,"p_female_smooth":0.995,"confidence":0.9091},{"year":1959,"F":1842,"M":7,"total":1849,"fixedness":0.886,"p_female_smooth":0.9909,"confidence":0.9024},{"year":1960,"F":1732,"M":9,"total":1741,"fixedness":0.8776,"p_female_smooth":0.9892,"confidence":0.897},{"year":1961,"F":1705,"M":7,"total":1712,"fixedness":0.8778,"p_female_smooth":0.9902,"confidence":0.8954},{"year":1962,"F":1649,"M":0,"total":1649,"fixedness":0.8811,"p_female_smooth":0.994,"confidence":0.8918},{"year":1963,"F":1583,"M":6,"total":1589,"fixedness":0.8705,"p_female_smooth":0.9901,"confidence":0.8882},{"year":1964,"F":1548,"M":5,"total":1553,"fixedness":0.869,"p_female_smooth":0.9905,"confidence":0.8859},{"year":1965,"F":1836,"M":8,"total":1844,"fixedness":0.8847,"p_female_smooth":0.9903,"confidence":0.9022},{"year":1966,"F":1467,"M":9,"total":1476,"fixedness":0.8583,"p_female_smooth":0.9873,"confidence":0.8807},{"year":1967,"F":1233,"M":0,"total":1233,"fixedness":0.8467,"p_female_smooth":0.992,"confidence":0.8604},{"year":1968,"F":1033,"M":0,"total":1033,"fixedness":0.8219,"p_female_smooth":0.9905,"confidence":0.8378},{"year":1969,"F":873,"M":0,"total":873,"fixedness":0.7954,"p_female_smooth":0.9888,"confidence":0.8136},{"year":1970,"F":805,"M":0,"total":805,"fixedness":0.7816,"p_female_smooth":0.9879,"confidence":0.801},{"year":1971,"F":652,"M":0,"total":652,"fixedness":0.7425,"p_female_smooth":0.9851,"confidence":0.7653},{"year":1972,"F":563,"M":0,"total":563,"fixedness":0.7126,"p_female_smooth":0.9828,"confidence":0.7379},{"year":1973,"F":494,"M":0,"total":494,"fixedness":0.6841,"p_female_smooth":0.9805,"confidence":0.7118},{"year":1974,"F":457,"M":5,"total":462,"fixedness":0.6544,"p_female_smooth":0.9689,"confidence":0.6979},{"year":1975,"F":436,"M":0,"total":436,"fixedness":0.6555,"p_female_smooth":0.9781,"confidence":0.6855},{"year":1976,"F":348,"M":0,"total":348,"fixedness":0.6005,"p_female_smooth":0.9728,"confidence":0.635},{"year":1977,"F":383,"M":0,"total":383,"fixedness":0.6243,"p_female_smooth":0.9752,"confidence":0.6569},{"year":1978,"F":360,"M":0,"total":360,"fixedness":0.609,"p_female_smooth":0.9737,"confidence":0.6429},{"year":1979,"F":345,"M":0,"total":345,"fixedness":0.5983,"p_female_smooth":0.9726,"confidence":0.633},{"year":1980,"F":350,"M":0,"total":350,"fixedness":0.602,"p_female_smooth":0.973,"confidence":0.6364},{"year":1981,"F":715,"M":0,"total":715,"fixedness":0.7602,"p_female_smooth":0.9864,"confidence":0.7814},{"year":1982,"F":780,"M":0,"total":780,"fixedness":0.776,"p_female_smooth":0.9875,"confidence":0.7959},{"year":1983,"F":639,"M":0,"total":639,"fixedness":0.7385,"p_female_smooth":0.9848,"confidence":0.7616},{"year":1984,"F":564,"M":0,"total":564,"fixedness":0.7129,"p_female_smooth":0.9829,"confidence":0.7382},{"year":1985,"F":522,"M":0,"total":522,"fixedness":0.6963,"p_female_smooth":0.9815,"confidence":0.723},{"year":1986,"F":604,"M":0,"total":604,"fixedness":0.7272,"p_female_smooth":0.984,"confidence":0.7512},{"year":1987,"F":564,"M":0,"total":564,"fixedness":0.7129,"p_female_smooth":0.9829,"confidence":0.7382},{"year":1988,"F":509,"M":7,"total":516,"fixedness":0.675,"p_female_smooth":0.9683,"confidence":0.7207},{"year":1989,"F":488,"M":5,"total":493,"fixedness":0.6698,"p_female_smooth":0.9708,"confidence":0.7114},{"year":1990,"F":475,"M":0,"total":475,"fixedness":0.6753,"p_female_smooth":0.9798,"confidence":0.7037},{"year":1991,"F":375,"M":0,"total":375,"fixedness":0.6192,"p_female_smooth":0.9747,"confidence":0.6522},{"year":1992,"F":342,"M":0,"total":342,"fixedness":0.5961,"p_female_smooth":0.9724,"confidence":0.631},{"year":1993,"F":306,"M":0,"total":306,"fixedness":0.5676,"p_female_smooth":0.9693,"confidence":0.6047},{"year":1994,"F":240,"M":0,"total":240,"fixedness":0.5035,"p_female_smooth":0.9615,"confidence":0.5455},{"year":1995,"F":273,"M":0,"total":273,"fixedness":0.5378,"p_female_smooth":0.9659,"confidence":0.5772},{"year":1996,"F":237,"M":0,"total":237,"fixedness":0.5001,"p_female_smooth":0.9611,"confidence":0.5423},{"year":1997,"F":220,"M":0,"total":220,"fixedness":0.4802,"p_female_smooth":0.9583,"confidence":0.5238},{"year":1998,"F":220,"M":0,"total":220,"fixedness":0.4802,"p_female_smooth":0.9583,"confidence":0.5238},{"year":1999,"F":205,"M":0,"total":205,"fixedness":0.4612,"p_female_smooth":0.9556,"confidence":0.5062},{"year":2000,"F":187,"M":0,"total":187,"fixedness":0.4365,"p_female_smooth":0.9517,"confidence":0.4832},{"year":2001,"F":165,"M":0,"total":165,"fixedness":0.4032,"p_female_smooth":0.9459,"confidence":0.4521},{"year":2002,"F":184,"M":0,"total":184,"fixedness":0.4322,"p_female_smooth":0.951,"confidence":0.4792},{"year":2003,"F":183,"M":0,"total":183,"fixedness":0.4307,"p_female_smooth":0.9507,"confidence":0.4778},{"year":2004,"F":202,"M":0,"total":202,"fixedness":0.4572,"p_female_smooth":0.955,"confidence":0.5025},{"year":2005,"F":185,"M":0,"total":185,"fixedness":0.4336,"p_female_smooth":0.9512,"confidence":0.4805},{"year":2006,"F":207,"M":0,"total":207,"fixedness":0.4638,"p_female_smooth":0.9559,"confidence":0.5086},{"year":2007,"F":189,"M":0,"total":189,"fixedness":0.4394,"p_female_smooth":0.9522,"confidence":0.4859},{"year":2008,"F":193,"M":0,"total":193,"fixedness":0.445,"p_female_smooth":0.9531,"confidence":0.4911},{"year":2009,"F":173,"M":0,"total":173,"fixedness":0.4157,"p_female_smooth":0.9482,"confidence":0.4638},{"year":2010,"F":151,"M":0,"total":151,"fixedness":0.3799,"p_female_smooth":0.9415,"confidence":0.4302},{"year":2011,"F":138,"M":0,"total":138,"fixedness":0.3566,"p_female_smooth":0.9367,"confidence":0.4083},{"year":2012,"F":165,"M":0,"total":165,"fixedness":0.4032,"p_female_smooth":0.9459,"confidence":0.4521},{"year":2013,"F":105,"M":0,"total":105,"fixedness":0.2892,"p_female_smooth":0.92,"confidence":0.3443},{"year":2014,"F":134,"M":0,"total":134,"fixedness":0.3491,"p_female_smooth":0.9351,"confidence":0.4012},{"year":2015,"F":144,"M":0,"total":144,"fixedness":0.3676,"p_female_smooth":0.939,"confidence":0.4186},{"year":2016,"F":152,"M":0,"total":152,"fixedness":0.3816,"p_female_smooth":0.9419,"confidence":0.4318},{"year":2017,"F":137,"M":0,"total":137,"fixedness":0.3547,"p_female_smooth":0.9363,"confidence":0.4065},{"year":2018,"F":123,"M":0,"total":123,"fixedness":0.3275,"p_female_smooth":0.9301,"confidence":0.3808},{"year":2019,"F":105,"M":0,"total":105,"fixedness":0.2892,"p_female_smooth":0.92,"confidence":0.3443},{"year":2020,"F":135,"M":0,"total":135,"fixedness":0.351,"p_female_smooth":0.9355,"confidence":0.403},{"year":2021,"F":110,"M":0,"total":110,"fixedness":0.3002,"p_female_smooth":0.9231,"confidence":0.3548},{"year":2022,"F":120,"M":0,"total":120,"fixedness":0.3214,"p_female_smooth":0.9286,"confidence":0.375},{"year":2023,"F":125,"M":0,"total":125,"fixedness":0.3316,"p_female_smooth":0.931,"confidence":0.3846},{"year":2024,"F":125,"M":0,"total":125,"fixedness":0.3316,"p_female_smooth":0.931,"confidence":0.3846}]}