{"name":"Cristian","alltime":{"total_F":1126,"total_M":69011,"total":70137,"fixedness":0.9649,"temporal_fixedness":0.8969,"stability":0.9295,"p_female_smooth":0.0162,"dominant_gender":"M","dominant_pct":98.4,"peak_year":2006,"peak_count":3045,"recent_avg_per_year":1028},"yearly":[{"year":1880,"F":0,"M":0,"total":0,"fixedness":0.0,"p_female_smooth":0.5,"confidence":0.0},{"year":1881,"F":0,"M":0,"total":0,"fixedness":0.0,"p_female_smooth":0.5,"confidence":0.0},{"year":1882,"F":0,"M":0,"total":0,"fixedness":0.0,"p_female_smooth":0.5,"confidence":0.0},{"year":1883,"F":0,"M":0,"total":0,"fixedness":0.0,"p_female_smooth":0.5,"confidence":0.0},{"year":1884,"F":0,"M":0,"total":0,"fixedness":0.0,"p_female_smooth":0.5,"confidence":0.0},{"year":1885,"F":0,"M":0,"total":0,"fixedness":0.0,"p_female_smooth":0.5,"confidence":0.0},{"year":1886,"F":0,"M":0,"total":0,"fixedness":0.0,"p_female_smooth":0.5,"confidence":0.0},{"year":1887,"F":0,"M":0,"total":0,"fixedness":0.0,"p_female_smooth":0.5,"confidence":0.0},{"year":1888,"F":0,"M":0,"total":0,"fixedness":0.0,"p_female_smooth":0.5,"confidence":0.0},{"year":1889,"F":0,"M":0,"total":0,"fixedness":0.0,"p_female_smooth":0.5,"confidence":0.0},{"year":1890,"F":0,"M":0,"total":0,"fixedness":0.0,"p_female_smooth":0.5,"confidence":0.0},{"year":1891,"F":0,"M":0,"total":0,"fixedness":0.0,"p_female_smooth":0.5,"confidence":0.0},{"year":1892,"F":0,"M":0,"total":0,"fixedness":0.0,"p_female_smooth":0.5,"confidence":0.0},{"year":1893,"F":0,"M":0,"total":0,"fixedness":0.0,"p_female_smooth":0.5,"confidence":0.0},{"year":1894,"F":0,"M":0,"total":0,"fixedness":0.0,"p_female_smooth":0.5,"confidence":0.0},{"year":1895,"F":0,"M":0,"total":0,"fixedness":0.0,"p_female_smooth":0.5,"confidence":0.0},{"year":1896,"F":0,"M":0,"total":0,"fixedness":0.0,"p_female_smooth":0.5,"confidence":0.0},{"year":1897,"F":0,"M":0,"total":0,"fixedness":0.0,"p_female_smooth":0.5,"confidence":0.0},{"year":1898,"F":0,"M":0,"total":0,"fixedness":0.0,"p_female_smooth":0.5,"confidence":0.0},{"year":1899,"F":0,"M":0,"total":0,"fixedness":0.0,"p_female_smooth":0.5,"confidence":0.0},{"year":1900,"F":0,"M":0,"total":0,"fixedness":0.0,"p_female_smooth":0.5,"confidence":0.0},{"year":1901,"F":0,"M":0,"total":0,"fixedness":0.0,"p_female_smooth":0.5,"confidence":0.0},{"year":1902,"F":0,"M":0,"total":0,"fixedness":0.0,"p_female_smooth":0.5,"confidence":0.0},{"year":1903,"F":0,"M":0,"total":0,"fixedness":0.0,"p_female_smooth":0.5,"confidence":0.0},{"year":1904,"F":0,"M":0,"total":0,"fixedness":0.0,"p_female_smooth":0.5,"confidence":0.0},{"year":1905,"F":0,"M":0,"total":0,"fixedness":0.0,"p_female_smooth":0.5,"confidence":0.0},{"year":1906,"F":0,"M":0,"total":0,"fixedness":0.0,"p_female_smooth":0.5,"confidence":0.0},{"year":1907,"F":0,"M":0,"total":0,"fixedness":0.0,"p_female_smooth":0.5,"confidence":0.0},{"year":1908,"F":0,"M":0,"total":0,"fixedness":0.0,"p_female_smooth":0.5,"confidence":0.0},{"year":1909,"F":0,"M":0,"total":0,"fixedness":0.0,"p_female_smooth":0.5,"confidence":0.0},{"year":1910,"F":0,"M":0,"total":0,"fixedness":0.0,"p_female_smooth":0.5,"confidence":0.0},{"year":1911,"F":0,"M":0,"total":0,"fixedness":0.0,"p_female_smooth":0.5,"confidence":0.0},{"year":1912,"F":0,"M":0,"total":0,"fixedness":0.0,"p_female_smooth":0.5,"confidence":0.0},{"year":1913,"F":0,"M":0,"total":0,"fixedness":0.0,"p_female_smooth":0.5,"confidence":0.0},{"year":1914,"F":0,"M":0,"total":0,"fixedness":0.0,"p_female_smooth":0.5,"confidence":0.0},{"year":1915,"F":0,"M":0,"total":0,"fixedness":0.0,"p_female_smooth":0.5,"confidence":0.0},{"year":1916,"F":0,"M":0,"total":0,"fixedness":0.0,"p_female_smooth":0.5,"confidence":0.0},{"year":1917,"F":0,"M":0,"total":0,"fixedness":0.0,"p_female_smooth":0.5,"confidence":0.0},{"year":1918,"F":0,"M":0,"total":0,"fixedness":0.0,"p_female_smooth":0.5,"confidence":0.0},{"year":1919,"F":0,"M":0,"total":0,"fixedness":0.0,"p_female_smooth":0.5,"confidence":0.0},{"year":1920,"F":0,"M":0,"total":0,"fixedness":0.0,"p_female_smooth":0.5,"confidence":0.0},{"year":1921,"F":0,"M":0,"total":0,"fixedness":0.0,"p_female_smooth":0.5,"confidence":0.0},{"year":1922,"F":0,"M":0,"total":0,"fixedness":0.0,"p_female_smooth":0.5,"confidence":0.0},{"year":1923,"F":0,"M":0,"total":0,"fixedness":0.0,"p_female_smooth":0.5,"confidence":0.0},{"year":1924,"F":0,"M":0,"total":0,"fixedness":0.0,"p_female_smooth":0.5,"confidence":0.0},{"year":1925,"F":0,"M":0,"total":0,"fixedness":0.0,"p_female_smooth":0.5,"confidence":0.0},{"year":1926,"F":0,"M":0,"total":0,"fixedness":0.0,"p_female_smooth":0.5,"confidence":0.0},{"year":1927,"F":0,"M":0,"total":0,"fixedness":0.0,"p_female_smooth":0.5,"confidence":0.0},{"year":1928,"F":0,"M":0,"total":0,"fixedness":0.0,"p_female_smooth":0.5,"confidence":0.0},{"year":1929,"F":0,"M":0,"total":0,"fixedness":0.0,"p_female_smooth":0.5,"confidence":0.0},{"year":1930,"F":0,"M":0,"total":0,"fixedness":0.0,"p_female_smooth":0.5,"confidence":0.0},{"year":1931,"F":0,"M":0,"total":0,"fixedness":0.0,"p_female_smooth":0.5,"confidence":0.0},{"year":1932,"F":0,"M":0,"total":0,"fixedness":0.0,"p_female_smooth":0.5,"confidence":0.0},{"year":1933,"F":0,"M":0,"total":0,"fixedness":0.0,"p_female_smooth":0.5,"confidence":0.0},{"year":1934,"F":0,"M":0,"total":0,"fixedness":0.0,"p_female_smooth":0.5,"confidence":0.0},{"year":1935,"F":0,"M":0,"total":0,"fixedness":0.0,"p_female_smooth":0.5,"confidence":0.0},{"year":1936,"F":0,"M":0,"total":0,"fixedness":0.0,"p_female_smooth":0.5,"confidence":0.0},{"year":1937,"F":0,"M":0,"total":0,"fixedness":0.0,"p_female_smooth":0.5,"confidence":0.0},{"year":1938,"F":0,"M":0,"total":0,"fixedness":0.0,"p_female_smooth":0.5,"confidence":0.0},{"year":1939,"F":0,"M":0,"total":0,"fixedness":0.0,"p_female_smooth":0.5,"confidence":0.0},{"year":1940,"F":0,"M":0,"total":0,"fixedness":0.0,"p_female_smooth":0.5,"confidence":0.0},{"year":1941,"F":0,"M":0,"total":0,"fixedness":0.0,"p_female_smooth":0.5,"confidence":0.0},{"year":1942,"F":0,"M":0,"total":0,"fixedness":0.0,"p_female_smooth":0.5,"confidence":0.0},{"year":1943,"F":0,"M":0,"total":0,"fixedness":0.0,"p_female_smooth":0.5,"confidence":0.0},{"year":1944,"F":0,"M":0,"total":0,"fixedness":0.0,"p_female_smooth":0.5,"confidence":0.0},{"year":1945,"F":0,"M":0,"total":0,"fixedness":0.0,"p_female_smooth":0.5,"confidence":0.0},{"year":1946,"F":0,"M":0,"total":0,"fixedness":0.0,"p_female_smooth":0.5,"confidence":0.0},{"year":1947,"F":0,"M":0,"total":0,"fixedness":0.0,"p_female_smooth":0.5,"confidence":0.0},{"year":1948,"F":0,"M":0,"total":0,"fixedness":0.0,"p_female_smooth":0.5,"confidence":0.0},{"year":1949,"F":0,"M":0,"total":0,"fixedness":0.0,"p_female_smooth":0.5,"confidence":0.0},{"year":1950,"F":0,"M":0,"total":0,"fixedness":0.0,"p_female_smooth":0.5,"confidence":0.0},{"year":1951,"F":0,"M":0,"total":0,"fixedness":0.0,"p_female_smooth":0.5,"confidence":0.0},{"year":1952,"F":0,"M":0,"total":0,"fixedness":0.0,"p_female_smooth":0.5,"confidence":0.0},{"year":1953,"F":0,"M":0,"total":0,"fixedness":0.0,"p_female_smooth":0.5,"confidence":0.0},{"year":1954,"F":0,"M":0,"total":0,"fixedness":0.0,"p_female_smooth":0.5,"confidence":0.0},{"year":1955,"F":0,"M":0,"total":0,"fixedness":0.0,"p_female_smooth":0.5,"confidence":0.0},{"year":1956,"F":0,"M":0,"total":0,"fixedness":0.0,"p_female_smooth":0.5,"confidence":0.0},{"year":1957,"F":0,"M":0,"total":0,"fixedness":0.0,"p_female_smooth":0.5,"confidence":0.0},{"year":1958,"F":0,"M":0,"total":0,"fixedness":0.0,"p_female_smooth":0.5,"confidence":0.0},{"year":1959,"F":0,"M":0,"total":0,"fixedness":0.0,"p_female_smooth":0.5,"confidence":0.0},{"year":1960,"F":0,"M":6,"total":6,"fixedness":0.0067,"p_female_smooth":0.3846,"confidence":0.0291},{"year":1961,"F":0,"M":5,"total":5,"fixedness":0.0049,"p_female_smooth":0.4,"confidence":0.0244},{"year":1962,"F":0,"M":0,"total":0,"fixedness":0.0,"p_female_smooth":0.5,"confidence":0.0},{"year":1963,"F":0,"M":0,"total":0,"fixedness":0.0,"p_female_smooth":0.5,"confidence":0.0},{"year":1964,"F":0,"M":7,"total":7,"fixedness":0.0088,"p_female_smooth":0.3704,"confidence":0.0338},{"year":1965,"F":0,"M":0,"total":0,"fixedness":0.0,"p_female_smooth":0.5,"confidence":0.0},{"year":1966,"F":0,"M":0,"total":0,"fixedness":0.0,"p_female_smooth":0.5,"confidence":0.0},{"year":1967,"F":0,"M":8,"total":8,"fixedness":0.011,"p_female_smooth":0.3571,"confidence":0.0385},{"year":1968,"F":0,"M":17,"total":17,"fixedness":0.036,"p_female_smooth":0.2703,"confidence":0.0783},{"year":1969,"F":0,"M":29,"total":29,"fixedness":0.0749,"p_female_smooth":0.2041,"confidence":0.1266},{"year":1970,"F":0,"M":18,"total":18,"fixedness":0.0391,"p_female_smooth":0.2632,"confidence":0.0826},{"year":1971,"F":0,"M":22,"total":22,"fixedness":0.0519,"p_female_smooth":0.2381,"confidence":0.0991},{"year":1972,"F":8,"M":54,"total":62,"fixedness":0.1327,"p_female_smooth":0.2195,"confidence":0.2366},{"year":1973,"F":8,"M":47,"total":55,"fixedness":0.1122,"p_female_smooth":0.24,"confidence":0.2157},{"year":1974,"F":0,"M":54,"total":54,"fixedness":0.1551,"p_female_smooth":0.1351,"confidence":0.2126},{"year":1975,"F":0,"M":54,"total":54,"fixedness":0.1551,"p_female_smooth":0.1351,"confidence":0.2126},{"year":1976,"F":11,"M":57,"total":68,"fixedness":0.1326,"p_female_smooth":0.2386,"confidence":0.2537},{"year":1977,"F":7,"M":75,"total":82,"fixedness":0.1939,"p_female_smooth":0.1667,"confidence":0.2908},{"year":1978,"F":0,"M":62,"total":62,"fixedness":0.1789,"p_female_smooth":0.122,"confidence":0.2366},{"year":1979,"F":0,"M":66,"total":66,"fixedness":0.1904,"p_female_smooth":0.1163,"confidence":0.2481},{"year":1980,"F":13,"M":108,"total":121,"fixedness":0.254,"p_female_smooth":0.1631,"confidence":0.3769},{"year":1981,"F":10,"M":119,"total":129,"fixedness":0.2868,"p_female_smooth":0.1342,"confidence":0.3921},{"year":1982,"F":13,"M":164,"total":177,"fixedness":0.3599,"p_female_smooth":0.1168,"confidence":0.4695},{"year":1983,"F":22,"M":145,"total":167,"fixedness":0.2993,"p_female_smooth":0.1711,"confidence":0.455},{"year":1984,"F":19,"M":167,"total":186,"fixedness":0.3462,"p_female_smooth":0.1408,"confidence":0.4819},{"year":1985,"F":25,"M":183,"total":208,"fixedness":0.3533,"p_female_smooth":0.1535,"confidence":0.5098},{"year":1986,"F":33,"M":234,"total":267,"fixedness":0.4004,"p_female_smooth":0.1498,"confidence":0.5717},{"year":1987,"F":19,"M":194,"total":213,"fixedness":0.3874,"p_female_smooth":0.1245,"confidence":0.5157},{"year":1988,"F":41,"M":245,"total":286,"fixedness":0.3923,"p_female_smooth":0.1667,"confidence":0.5885},{"year":1989,"F":57,"M":391,"total":448,"fixedness":0.4934,"p_female_smooth":0.1432,"confidence":0.6914},{"year":1990,"F":58,"M":550,"total":608,"fixedness":0.5895,"p_female_smooth":0.1083,"confidence":0.7525},{"year":1991,"F":83,"M":669,"total":752,"fixedness":0.5996,"p_female_smooth":0.1205,"confidence":0.7899},{"year":1992,"F":58,"M":1048,"total":1106,"fixedness":0.7446,"p_female_smooth":0.0604,"confidence":0.8469},{"year":1993,"F":73,"M":1786,"total":1859,"fixedness":0.8231,"p_female_smooth":0.0442,"confidence":0.9029},{"year":1994,"F":73,"M":2542,"total":2615,"fixedness":0.8704,"p_female_smooth":0.0315,"confidence":0.929},{"year":1995,"F":67,"M":2848,"total":2915,"fixedness":0.8867,"p_female_smooth":0.0262,"confidence":0.9358},{"year":1996,"F":56,"M":2847,"total":2903,"fixedness":0.8933,"p_female_smooth":0.0226,"confidence":0.9355},{"year":1997,"F":42,"M":2331,"total":2373,"fixedness":0.8822,"p_female_smooth":0.0217,"confidence":0.9223},{"year":1998,"F":29,"M":2565,"total":2594,"fixedness":0.9007,"p_female_smooth":0.0149,"confidence":0.9284},{"year":1999,"F":31,"M":2341,"total":2372,"fixedness":0.8906,"p_female_smooth":0.0171,"confidence":0.9222},{"year":2000,"F":45,"M":2423,"total":2468,"fixedness":0.8841,"p_female_smooth":0.0221,"confidence":0.925},{"year":2001,"F":28,"M":2630,"total":2658,"fixedness":0.9036,"p_female_smooth":0.0142,"confidence":0.93},{"year":2002,"F":23,"M":2685,"total":2708,"fixedness":0.9087,"p_female_smooth":0.0121,"confidence":0.9312},{"year":2003,"F":21,"M":2805,"total":2826,"fixedness":0.9136,"p_female_smooth":0.0109,"confidence":0.9339},{"year":2004,"F":16,"M":2856,"total":2872,"fixedness":0.9181,"p_female_smooth":0.009,"confidence":0.9349},{"year":2005,"F":26,"M":2745,"total":2771,"fixedness":0.9086,"p_female_smooth":0.0129,"confidence":0.9327},{"year":2006,"F":22,"M":3023,"total":3045,"fixedness":0.9188,"p_female_smooth":0.0104,"confidence":0.9384},{"year":2007,"F":10,"M":2918,"total":2928,"fixedness":0.9234,"p_female_smooth":0.0068,"confidence":0.9361},{"year":2008,"F":7,"M":2702,"total":2709,"fixedness":0.9196,"p_female_smooth":0.0062,"confidence":0.9312},{"year":2009,"F":14,"M":2399,"total":2413,"fixedness":0.9052,"p_female_smooth":0.0099,"confidence":0.9235},{"year":2010,"F":12,"M":2069,"total":2081,"fixedness":0.8932,"p_female_smooth":0.0105,"confidence":0.9123},{"year":2011,"F":9,"M":2007,"total":2016,"fixedness":0.8928,"p_female_smooth":0.0093,"confidence":0.9097},{"year":2012,"F":7,"M":1675,"total":1682,"fixedness":0.8759,"p_female_smooth":0.01,"confidence":0.8937},{"year":2013,"F":6,"M":1537,"total":1543,"fixedness":0.8671,"p_female_smooth":0.0102,"confidence":0.8853},{"year":2014,"F":0,"M":1346,"total":1346,"fixedness":0.8579,"p_female_smooth":0.0073,"confidence":0.8706},{"year":2015,"F":6,"M":1350,"total":1356,"fixedness":0.8512,"p_female_smooth":0.0116,"confidence":0.8715},{"year":2016,"F":7,"M":1214,"total":1221,"fixedness":0.8357,"p_female_smooth":0.0137,"confidence":0.8593},{"year":2017,"F":6,"M":1184,"total":1190,"fixedness":0.8335,"p_female_smooth":0.0132,"confidence":0.8561},{"year":2018,"F":0,"M":1141,"total":1141,"fixedness":0.8362,"p_female_smooth":0.0086,"confidence":0.8509},{"year":2019,"F":0,"M":1110,"total":1110,"fixedness":0.8323,"p_female_smooth":0.0088,"confidence":0.8473},{"year":2020,"F":5,"M":988,"total":993,"fixedness":0.8077,"p_female_smooth":0.0148,"confidence":0.8324},{"year":2021,"F":0,"M":993,"total":993,"fixedness":0.8159,"p_female_smooth":0.0099,"confidence":0.8324},{"year":2022,"F":0,"M":1046,"total":1046,"fixedness":0.8237,"p_female_smooth":0.0094,"confidence":0.8395},{"year":2023,"F":0,"M":1029,"total":1029,"fixedness":0.8213,"p_female_smooth":0.0095,"confidence":0.8373},{"year":2024,"F":0,"M":1078,"total":1078,"fixedness":0.8281,"p_female_smooth":0.0091,"confidence":0.8435}]}