{"name":"Joanna","alltime":{"total_F":110756,"total_M":306,"total":111062,"fixedness":0.9925,"temporal_fixedness":0.9824,"stability":0.9898,"p_female_smooth":0.9972,"dominant_gender":"F","dominant_pct":99.7,"peak_year":1984,"peak_count":3353,"recent_avg_per_year":1028},"yearly":[{"year":1880,"F":26,"M":0,"total":26,"fixedness":0.065,"p_female_smooth":0.7826,"confidence":0.115},{"year":1881,"F":21,"M":0,"total":21,"fixedness":0.0487,"p_female_smooth":0.7561,"confidence":0.095},{"year":1882,"F":15,"M":0,"total":15,"fixedness":0.0299,"p_female_smooth":0.7143,"confidence":0.0698},{"year":1883,"F":33,"M":0,"total":33,"fixedness":0.0882,"p_female_smooth":0.8113,"confidence":0.1416},{"year":1884,"F":24,"M":0,"total":24,"fixedness":0.0584,"p_female_smooth":0.7727,"confidence":0.1071},{"year":1885,"F":40,"M":0,"total":40,"fixedness":0.1111,"p_female_smooth":0.8333,"confidence":0.1667},{"year":1886,"F":35,"M":0,"total":35,"fixedness":0.0948,"p_female_smooth":0.8182,"confidence":0.1489},{"year":1887,"F":32,"M":0,"total":32,"fixedness":0.0849,"p_female_smooth":0.8077,"confidence":0.1379},{"year":1888,"F":37,"M":0,"total":37,"fixedness":0.1013,"p_female_smooth":0.8246,"confidence":0.1561},{"year":1889,"F":27,"M":0,"total":27,"fixedness":0.0683,"p_female_smooth":0.7872,"confidence":0.1189},{"year":1890,"F":33,"M":0,"total":33,"fixedness":0.0882,"p_female_smooth":0.8113,"confidence":0.1416},{"year":1891,"F":36,"M":0,"total":36,"fixedness":0.0981,"p_female_smooth":0.8214,"confidence":0.1525},{"year":1892,"F":42,"M":0,"total":42,"fixedness":0.1176,"p_female_smooth":0.8387,"confidence":0.1736},{"year":1893,"F":36,"M":0,"total":36,"fixedness":0.0981,"p_female_smooth":0.8214,"confidence":0.1525},{"year":1894,"F":44,"M":0,"total":44,"fixedness":0.124,"p_female_smooth":0.8438,"confidence":0.1803},{"year":1895,"F":29,"M":0,"total":29,"fixedness":0.0749,"p_female_smooth":0.7959,"confidence":0.1266},{"year":1896,"F":37,"M":0,"total":37,"fixedness":0.1013,"p_female_smooth":0.8246,"confidence":0.1561},{"year":1897,"F":50,"M":0,"total":50,"fixedness":0.1429,"p_female_smooth":0.8571,"confidence":0.2},{"year":1898,"F":42,"M":0,"total":42,"fixedness":0.1176,"p_female_smooth":0.8387,"confidence":0.1736},{"year":1899,"F":40,"M":0,"total":40,"fixedness":0.1111,"p_female_smooth":0.8333,"confidence":0.1667},{"year":1900,"F":37,"M":0,"total":37,"fixedness":0.1013,"p_female_smooth":0.8246,"confidence":0.1561},{"year":1901,"F":31,"M":0,"total":31,"fixedness":0.0816,"p_female_smooth":0.8039,"confidence":0.1342},{"year":1902,"F":26,"M":0,"total":26,"fixedness":0.065,"p_female_smooth":0.7826,"confidence":0.115},{"year":1903,"F":45,"M":0,"total":45,"fixedness":0.1272,"p_female_smooth":0.8462,"confidence":0.1837},{"year":1904,"F":37,"M":0,"total":37,"fixedness":0.1013,"p_female_smooth":0.8246,"confidence":0.1561},{"year":1905,"F":41,"M":0,"total":41,"fixedness":0.1143,"p_female_smooth":0.8361,"confidence":0.1701},{"year":1906,"F":40,"M":0,"total":40,"fixedness":0.1111,"p_female_smooth":0.8333,"confidence":0.1667},{"year":1907,"F":32,"M":0,"total":32,"fixedness":0.0849,"p_female_smooth":0.8077,"confidence":0.1379},{"year":1908,"F":54,"M":0,"total":54,"fixedness":0.1551,"p_female_smooth":0.8649,"confidence":0.2126},{"year":1909,"F":48,"M":0,"total":48,"fixedness":0.1366,"p_female_smooth":0.8529,"confidence":0.1935},{"year":1910,"F":49,"M":0,"total":49,"fixedness":0.1397,"p_female_smooth":0.8551,"confidence":0.1968},{"year":1911,"F":59,"M":0,"total":59,"fixedness":0.1701,"p_female_smooth":0.8734,"confidence":0.2278},{"year":1912,"F":73,"M":0,"total":73,"fixedness":0.2099,"p_female_smooth":0.8925,"confidence":0.2674},{"year":1913,"F":94,"M":0,"total":94,"fixedness":0.2636,"p_female_smooth":0.9123,"confidence":0.3197},{"year":1914,"F":81,"M":0,"total":81,"fixedness":0.2312,"p_female_smooth":0.901,"confidence":0.2883},{"year":1915,"F":147,"M":0,"total":147,"fixedness":0.3729,"p_female_smooth":0.9401,"confidence":0.4236},{"year":1916,"F":168,"M":0,"total":168,"fixedness":0.408,"p_female_smooth":0.9468,"confidence":0.4565},{"year":1917,"F":170,"M":0,"total":170,"fixedness":0.4111,"p_female_smooth":0.9474,"confidence":0.4595},{"year":1918,"F":180,"M":0,"total":180,"fixedness":0.4263,"p_female_smooth":0.95,"confidence":0.4737},{"year":1919,"F":165,"M":0,"total":165,"fixedness":0.4032,"p_female_smooth":0.9459,"confidence":0.4521},{"year":1920,"F":167,"M":0,"total":167,"fixedness":0.4064,"p_female_smooth":0.9465,"confidence":0.455},{"year":1921,"F":160,"M":0,"total":160,"fixedness":0.3951,"p_female_smooth":0.9444,"confidence":0.4444},{"year":1922,"F":185,"M":0,"total":185,"fixedness":0.4336,"p_female_smooth":0.9512,"confidence":0.4805},{"year":1923,"F":199,"M":0,"total":199,"fixedness":0.4532,"p_female_smooth":0.9543,"confidence":0.4987},{"year":1924,"F":208,"M":0,"total":208,"fixedness":0.4651,"p_female_smooth":0.9561,"confidence":0.5098},{"year":1925,"F":236,"M":0,"total":236,"fixedness":0.499,"p_female_smooth":0.9609,"confidence":0.5413},{"year":1926,"F":281,"M":0,"total":281,"fixedness":0.5454,"p_female_smooth":0.9668,"confidence":0.5842},{"year":1927,"F":238,"M":0,"total":238,"fixedness":0.5013,"p_female_smooth":0.9612,"confidence":0.5434},{"year":1928,"F":285,"M":0,"total":285,"fixedness":0.5491,"p_female_smooth":0.9672,"confidence":0.5876},{"year":1929,"F":274,"M":0,"total":274,"fixedness":0.5387,"p_female_smooth":0.966,"confidence":0.5781},{"year":1930,"F":359,"M":0,"total":359,"fixedness":0.6083,"p_female_smooth":0.9736,"confidence":0.6422},{"year":1931,"F":331,"M":0,"total":331,"fixedness":0.5878,"p_female_smooth":0.9715,"confidence":0.6234},{"year":1932,"F":337,"M":0,"total":337,"fixedness":0.5924,"p_female_smooth":0.972,"confidence":0.6276},{"year":1933,"F":367,"M":0,"total":367,"fixedness":0.6138,"p_female_smooth":0.9742,"confidence":0.6473},{"year":1934,"F":480,"M":0,"total":480,"fixedness":0.6776,"p_female_smooth":0.98,"confidence":0.7059},{"year":1935,"F":424,"M":0,"total":424,"fixedness":0.6489,"p_female_smooth":0.9775,"confidence":0.6795},{"year":1936,"F":361,"M":0,"total":361,"fixedness":0.6097,"p_female_smooth":0.9738,"confidence":0.6435},{"year":1937,"F":438,"M":0,"total":438,"fixedness":0.6565,"p_female_smooth":0.9782,"confidence":0.6865},{"year":1938,"F":427,"M":0,"total":427,"fixedness":0.6506,"p_female_smooth":0.9776,"confidence":0.681},{"year":1939,"F":390,"M":0,"total":390,"fixedness":0.6288,"p_female_smooth":0.9756,"confidence":0.661},{"year":1940,"F":412,"M":0,"total":412,"fixedness":0.642,"p_female_smooth":0.9769,"confidence":0.6732},{"year":1941,"F":417,"M":0,"total":417,"fixedness":0.6449,"p_female_smooth":0.9771,"confidence":0.6759},{"year":1942,"F":502,"M":0,"total":502,"fixedness":0.6877,"p_female_smooth":0.9808,"confidence":0.7151},{"year":1943,"F":514,"M":0,"total":514,"fixedness":0.6929,"p_female_smooth":0.9813,"confidence":0.7199},{"year":1944,"F":454,"M":0,"total":454,"fixedness":0.6649,"p_female_smooth":0.9789,"confidence":0.6942},{"year":1945,"F":425,"M":0,"total":425,"fixedness":0.6494,"p_female_smooth":0.9775,"confidence":0.68},{"year":1946,"F":498,"M":0,"total":498,"fixedness":0.6859,"p_female_smooth":0.9807,"confidence":0.7135},{"year":1947,"F":509,"M":0,"total":509,"fixedness":0.6908,"p_female_smooth":0.9811,"confidence":0.7179},{"year":1948,"F":515,"M":0,"total":515,"fixedness":0.6934,"p_female_smooth":0.9813,"confidence":0.7203},{"year":1949,"F":463,"M":0,"total":463,"fixedness":0.6694,"p_female_smooth":0.9793,"confidence":0.6983},{"year":1950,"F":478,"M":0,"total":478,"fixedness":0.6767,"p_female_smooth":0.9799,"confidence":0.705},{"year":1951,"F":445,"M":0,"total":445,"fixedness":0.6602,"p_female_smooth":0.9785,"confidence":0.6899},{"year":1952,"F":407,"M":0,"total":407,"fixedness":0.6391,"p_female_smooth":0.9766,"confidence":0.6705},{"year":1953,"F":411,"M":0,"total":411,"fixedness":0.6415,"p_female_smooth":0.9768,"confidence":0.6727},{"year":1954,"F":471,"M":0,"total":471,"fixedness":0.6733,"p_female_smooth":0.9796,"confidence":0.7019},{"year":1955,"F":455,"M":0,"total":455,"fixedness":0.6654,"p_female_smooth":0.9789,"confidence":0.6947},{"year":1956,"F":482,"M":0,"total":482,"fixedness":0.6786,"p_female_smooth":0.9801,"confidence":0.7067},{"year":1957,"F":582,"M":0,"total":582,"fixedness":0.7195,"p_female_smooth":0.9834,"confidence":0.7442},{"year":1958,"F":665,"M":0,"total":665,"fixedness":0.7463,"p_female_smooth":0.9854,"confidence":0.7688},{"year":1959,"F":755,"M":0,"total":755,"fixedness":0.7702,"p_female_smooth":0.9871,"confidence":0.7906},{"year":1960,"F":820,"M":0,"total":820,"fixedness":0.7848,"p_female_smooth":0.9881,"confidence":0.8039},{"year":1961,"F":865,"M":0,"total":865,"fixedness":0.7939,"p_female_smooth":0.9887,"confidence":0.8122},{"year":1962,"F":834,"M":0,"total":834,"fixedness":0.7877,"p_female_smooth":0.9883,"confidence":0.8066},{"year":1963,"F":888,"M":0,"total":888,"fixedness":0.7982,"p_female_smooth":0.989,"confidence":0.8162},{"year":1964,"F":878,"M":0,"total":878,"fixedness":0.7963,"p_female_smooth":0.9889,"confidence":0.8145},{"year":1965,"F":909,"M":0,"total":909,"fixedness":0.802,"p_female_smooth":0.9892,"confidence":0.8197},{"year":1966,"F":890,"M":0,"total":890,"fixedness":0.7986,"p_female_smooth":0.989,"confidence":0.8165},{"year":1967,"F":858,"M":7,"total":865,"fixedness":0.781,"p_female_smooth":0.9808,"confidence":0.8122},{"year":1968,"F":1035,"M":0,"total":1035,"fixedness":0.8222,"p_female_smooth":0.9905,"confidence":0.8381},{"year":1969,"F":1217,"M":5,"total":1222,"fixedness":0.8386,"p_female_smooth":0.9879,"confidence":0.8594},{"year":1970,"F":1331,"M":5,"total":1336,"fixedness":0.8505,"p_female_smooth":0.9889,"confidence":0.8698},{"year":1971,"F":1372,"M":0,"total":1372,"fixedness":0.8602,"p_female_smooth":0.9928,"confidence":0.8728},{"year":1972,"F":1423,"M":0,"total":1423,"fixedness":0.8646,"p_female_smooth":0.9931,"confidence":0.8768},{"year":1973,"F":1664,"M":0,"total":1664,"fixedness":0.8821,"p_female_smooth":0.9941,"confidence":0.8927},{"year":1974,"F":1772,"M":7,"total":1779,"fixedness":0.8819,"p_female_smooth":0.9906,"confidence":0.8989},{"year":1975,"F":1699,"M":6,"total":1705,"fixedness":0.8784,"p_female_smooth":0.9907,"confidence":0.895},{"year":1976,"F":1718,"M":7,"total":1725,"fixedness":0.8786,"p_female_smooth":0.9903,"confidence":0.8961},{"year":1977,"F":1565,"M":0,"total":1565,"fixedness":0.8755,"p_female_smooth":0.9937,"confidence":0.8867},{"year":1978,"F":1349,"M":7,"total":1356,"fixedness":0.8499,"p_female_smooth":0.9876,"confidence":0.8715},{"year":1979,"F":1388,"M":10,"total":1398,"fixedness":0.8502,"p_female_smooth":0.9859,"confidence":0.8748},{"year":1980,"F":1726,"M":8,"total":1734,"fixedness":0.8782,"p_female_smooth":0.9897,"confidence":0.8966},{"year":1981,"F":1827,"M":10,"total":1837,"fixedness":0.8824,"p_female_smooth":0.9892,"confidence":0.9018},{"year":1982,"F":1834,"M":14,"total":1848,"fixedness":0.8792,"p_female_smooth":0.9872,"confidence":0.9023},{"year":1983,"F":2120,"M":7,"total":2127,"fixedness":0.8996,"p_female_smooth":0.9921,"confidence":0.9141},{"year":1984,"F":3332,"M":21,"total":3353,"fixedness":0.9264,"p_female_smooth":0.9908,"confidence":0.9437},{"year":1985,"F":2772,"M":23,"total":2795,"fixedness":0.9113,"p_female_smooth":0.9883,"confidence":0.9332},{"year":1986,"F":2227,"M":20,"total":2247,"fixedness":0.894,"p_female_smooth":0.9868,"confidence":0.9183},{"year":1987,"F":2056,"M":20,"total":2076,"fixedness":0.886,"p_female_smooth":0.9857,"confidence":0.9121},{"year":1988,"F":2206,"M":15,"total":2221,"fixedness":0.8969,"p_female_smooth":0.9888,"confidence":0.9174},{"year":1989,"F":2116,"M":16,"total":2132,"fixedness":0.8921,"p_female_smooth":0.9879,"confidence":0.9142},{"year":1990,"F":2230,"M":11,"total":2241,"fixedness":0.901,"p_female_smooth":0.9907,"confidence":0.9181},{"year":1991,"F":1951,"M":11,"total":1962,"fixedness":0.8883,"p_female_smooth":0.9894,"confidence":0.9075},{"year":1992,"F":1825,"M":14,"total":1839,"fixedness":0.8786,"p_female_smooth":0.9871,"confidence":0.9019},{"year":1993,"F":1638,"M":11,"total":1649,"fixedness":0.8694,"p_female_smooth":0.9874,"confidence":0.8918},{"year":1994,"F":1624,"M":7,"total":1631,"fixedness":0.8724,"p_female_smooth":0.9897,"confidence":0.8908},{"year":1995,"F":1597,"M":8,"total":1605,"fixedness":0.8695,"p_female_smooth":0.9889,"confidence":0.8892},{"year":1996,"F":1405,"M":0,"total":1405,"fixedness":0.8631,"p_female_smooth":0.993,"confidence":0.8754},{"year":1997,"F":1409,"M":0,"total":1409,"fixedness":0.8634,"p_female_smooth":0.993,"confidence":0.8757},{"year":1998,"F":1281,"M":0,"total":1281,"fixedness":0.8517,"p_female_smooth":0.9923,"confidence":0.865},{"year":1999,"F":1327,"M":7,"total":1334,"fixedness":0.8478,"p_female_smooth":0.9874,"confidence":0.8696},{"year":2000,"F":1349,"M":0,"total":1349,"fixedness":0.8582,"p_female_smooth":0.9927,"confidence":0.8709},{"year":2001,"F":1555,"M":5,"total":1560,"fixedness":0.8695,"p_female_smooth":0.9905,"confidence":0.8864},{"year":2002,"F":1335,"M":0,"total":1335,"fixedness":0.8569,"p_female_smooth":0.9926,"confidence":0.8697},{"year":2003,"F":1303,"M":6,"total":1309,"fixedness":0.8466,"p_female_smooth":0.988,"confidence":0.8675},{"year":2004,"F":1279,"M":8,"total":1287,"fixedness":0.8417,"p_female_smooth":0.9862,"confidence":0.8655},{"year":2005,"F":1167,"M":0,"total":1167,"fixedness":0.8393,"p_female_smooth":0.9916,"confidence":0.8537},{"year":2006,"F":1289,"M":0,"total":1289,"fixedness":0.8525,"p_female_smooth":0.9924,"confidence":0.8657},{"year":2007,"F":1392,"M":0,"total":1392,"fixedness":0.862,"p_female_smooth":0.9929,"confidence":0.8744},{"year":2008,"F":1194,"M":0,"total":1194,"fixedness":0.8424,"p_female_smooth":0.9918,"confidence":0.8565},{"year":2009,"F":1106,"M":5,"total":1111,"fixedness":0.825,"p_female_smooth":0.9867,"confidence":0.8474},{"year":2010,"F":1066,"M":0,"total":1066,"fixedness":0.8265,"p_female_smooth":0.9908,"confidence":0.842},{"year":2011,"F":976,"M":0,"total":976,"fixedness":0.8133,"p_female_smooth":0.99,"confidence":0.8299},{"year":2012,"F":974,"M":0,"total":974,"fixedness":0.8129,"p_female_smooth":0.9899,"confidence":0.8296},{"year":2013,"F":945,"M":0,"total":945,"fixedness":0.8082,"p_female_smooth":0.9896,"confidence":0.8253},{"year":2014,"F":1022,"M":5,"total":1027,"fixedness":0.813,"p_female_smooth":0.9857,"confidence":0.837},{"year":2015,"F":1065,"M":0,"total":1065,"fixedness":0.8264,"p_female_smooth":0.9908,"confidence":0.8419},{"year":2016,"F":1274,"M":0,"total":1274,"fixedness":0.851,"p_female_smooth":0.9923,"confidence":0.8643},{"year":2017,"F":1352,"M":0,"total":1352,"fixedness":0.8584,"p_female_smooth":0.9927,"confidence":0.8711},{"year":2018,"F":1454,"M":0,"total":1454,"fixedness":0.8672,"p_female_smooth":0.9932,"confidence":0.8791},{"year":2019,"F":1280,"M":0,"total":1280,"fixedness":0.8516,"p_female_smooth":0.9923,"confidence":0.8649},{"year":2020,"F":1175,"M":0,"total":1175,"fixedness":0.8402,"p_female_smooth":0.9916,"confidence":0.8545},{"year":2021,"F":1101,"M":0,"total":1101,"fixedness":0.8312,"p_female_smooth":0.9911,"confidence":0.8463},{"year":2022,"F":1002,"M":0,"total":1002,"fixedness":0.8173,"p_female_smooth":0.9902,"confidence":0.8336},{"year":2023,"F":918,"M":0,"total":918,"fixedness":0.8036,"p_female_smooth":0.9893,"confidence":0.8211},{"year":2024,"F":942,"M":0,"total":942,"fixedness":0.8077,"p_female_smooth":0.9896,"confidence":0.8249}]}